vegafusion_python_embed-1.6.9.dist-info/METADATA
vegafusion_python_embed-1.6.9.dist-info/WHEEL
vegafusion_embed/__init__.py
vegafusion_embed/vegafusion_embed.abi3.so
vegafusion_python_embed-1.6.9.dist-info/RECORD
