Metadata-Version: 2.3
Name: vegafusion-python-embed
Version: 1.6.9
Summary: vegafusion-python-embed PyO3 Python Package
License: BSD-3-Clause
